pcache/__init__.py
pcache/pcache.py
pcache-0.0.3.dist-info/LICENSE
pcache-0.0.3.dist-info/METADATA
pcache-0.0.3.dist-info/WHEEL
pcache-0.0.3.dist-info/top_level.txt
pcache-0.0.3.dist-info/RECORD
